mango/__init__.py
mango/odm.py
mango/utils.py
mangodb_py-1.0.0.dist-info/METADATA
mangodb_py-1.0.0.dist-info/WHEEL
mangodb_py-1.0.0.dist-info/top_level.txt
mangodb_py-1.0.0.dist-info/RECORD
